nodeconductor_auth_valimo/__init__.py
nodeconductor_auth_valimo/admin.py
nodeconductor_auth_valimo/apps.py
nodeconductor_auth_valimo/client.py
nodeconductor_auth_valimo/executors.py
nodeconductor_auth_valimo/extension.py
nodeconductor_auth_valimo/filters.py
nodeconductor_auth_valimo/models.py
nodeconductor_auth_valimo/perms.py
nodeconductor_auth_valimo/serializers.py
nodeconductor_auth_valimo/tasks.py
nodeconductor_auth_valimo/urls.py
nodeconductor_auth_valimo/views.py
nodeconductor_auth_valimo/migrations/0001_initial.py
nodeconductor_auth_valimo/migrations/__init__.py
nodeconductor_auth_valimo-0.2.0.dist-info/DESCRIPTION.rst
nodeconductor_auth_valimo-0.2.0.dist-info/METADATA
nodeconductor_auth_valimo-0.2.0.dist-info/RECORD
nodeconductor_auth_valimo-0.2.0.dist-info/WHEEL
nodeconductor_auth_valimo-0.2.0.dist-info/entry_points.txt
nodeconductor_auth_valimo-0.2.0.dist-info/metadata.json
nodeconductor_auth_valimo-0.2.0.dist-info/top_level.txt
